{
  "coins": [
    "BTC",
    "ETH",
    "SOL",
    "HYPE",
    "XRP",
    "DOGE",
    "SUI",
    "LINK",
    "AVAX"
  ],
  "data": {
    "BTC": {
      "currentPrice": 67919.0,
      "longLiquidations": [
        {
          "price": 52840.98,
          "value": 29425319.86449,
          "cumulative": 76616433.526655,
          "10x": 0,
          "25x": 0,
          "50x": 29425319.86449,
          "100x": 0
        },
        {
          "price": 55286.07,
          "value": 1257704.0,
          "cumulative": 47191113.662165,
          "10x": 0,
          "25x": 1257704.0,
          "50x": 0,
          "100x": 0
        },
        {
          "price": 56916.12,
          "value": 19845182.5,
          "cumulative": 45933409.662165,
          "10x": 0,
          "25x": 19845182.5,
          "50x": 0,
          "100x": 0
        },
        {
          "price": 62621.32,
          "value": 7305061.064831,
          "cumulative": 26088227.162165,
          "10x": 3258733.528956,
          "25x": 0,
          "50x": 4046327.535875,
          "100x": 0
        },
        {
          "price": 63436.35,
          "value": 18457431.19176,
          "cumulative": 18783166.097334,
          "10x": 0,
          "25x": 1371720.0,
          "50x": 17085711.19176,
          "100x": 0
        },
        {
          "price": 67511.49,
          "value": 325734.905574,
          "cumulative": 325734.905574,
          "10x": 0,
          "25x": 0,
          "50x": 325734.905574,
          "100x": 0
        }
      ],
      "shortLiquidations": [
        {
          "price": 69141.54,
          "value": 5838429.53874,
          "cumulative": 5838429.53874,
          "10x": 0,
          "25x": 0,
          "50x": 5838429.53874,
          "100x": 0
        },
        {
          "price": 69956.57,
          "value": 786941.7693719999,
          "cumulative": 6625371.308111999,
          "10x": 0,
          "25x": 786941.7693719999,
          "50x": 0,
          "100x": 0
        },
        {
          "price": 70771.6,
          "value": 2719720.0,
          "cumulative": 9345091.308112,
          "10x": 0,
          "25x": 0,
          "50x": 2719720.0,
          "100x": 0
        },
        {
          "price": 74031.71,
          "value": 37169165.0,
          "cumulative": 46514256.308111995,
          "10x": 0,
          "25x": 37169165.0,
          "50x": 0,
          "100x": 0
        },
        {
          "price": 80551.93,
          "value": 6850000.0,
          "cumulative": 53364256.308111995,
          "10x": 0,
          "25x": 0,
          "50x": 6850000.0,
          "100x": 0
        },
        {
          "price": 87887.19,
          "value": 4976393.11768,
          "cumulative": 58340649.425791994,
          "10x": 0,
          "25x": 0,
          "50x": 4976393.11768,
          "100x": 0
        }
      ],
      "totalLongValue": 76616433.52665499,
      "totalShortValue": 58340649.425792,
      "positionCount": 41
    },
    "ETH": {
      "currentPrice": 1965.8,
      "longLiquidations": [
        {
          "price": 1529.39,
          "value": 4945150.0,
          "cumulative": 31298210.186646,
          "10x": 0,
          "25x": 4945150.0,
          "50x": 0,
          "100x": 0
        },
        {
          "price": 1600.16,
          "value": 1233543.75,
          "cumulative": 26353060.186646,
          "10x": 0,
          "25x": 1233543.75,
          "50x": 0,
          "100x": 0
        },
        {
          "price": 1623.75,
          "value": 355806.0,
          "cumulative": 25119516.436646,
          "10x": 0,
          "25x": 355806.0,
          "50x": 0,
          "100x": 0
        },
        {
          "price": 1741.7,
          "value": 3149000.9158299994,
          "cumulative": 24763710.436646,
          "10x": 0,
          "25x": 3149000.9158299994,
          "50x": 0,
          "100x": 0
        },
        {
          "price": 1836.06,
          "value": 674728.8231200001,
          "cumulative": 21614709.520816002,
          "10x": 0,
          "25x": 674728.8231200001,
          "50x": 0,
          "100x": 0
        },
        {
          "price": 1859.65,
          "value": 3358452.0,
          "cumulative": 20939980.697696,
          "10x": 0,
          "25x": 3358452.0,
          "50x": 0,
          "100x": 0
        },
        {
          "price": 1906.83,
          "value": 17581528.697696,
          "cumulative": 17581528.697696,
          "10x": 0,
          "25x": 17581528.697696,
          "50x": 0,
          "100x": 0
        }
      ],
      "shortLiquidations": [
        {
          "price": 2119.13,
          "value": 5607425.647985001,
          "cumulative": 5607425.647985001,
          "10x": 0,
          "25x": 5607425.647985001,
          "50x": 0,
          "100x": 0
        },
        {
          "price": 2307.85,
          "value": 19646500.0,
          "cumulative": 25253925.647985,
          "10x": 0,
          "25x": 19646500.0,
          "50x": 0,
          "100x": 0
        },
        {
          "price": 2472.98,
          "value": 10498565.0,
          "cumulative": 35752490.647985,
          "10x": 0,
          "25x": 10498565.0,
          "50x": 0,
          "100x": 0
        }
      ],
      "totalLongValue": 31298210.186646,
      "totalShortValue": 35752490.647985004,
      "positionCount": 44
    },
    "SOL": {
      "currentPrice": 84.453,
      "longLiquidations": [],
      "shortLiquidations": [],
      "totalLongValue": 0,
      "totalShortValue": 0,
      "positionCount": 19
    },
    "HYPE": {
      "currentPrice": 29.208,
      "longLiquidations": [
        {
          "price": 24.83,
          "value": 256570.09870199996,
          "cumulative": 501897.794946,
          "10x": 256570.09870199996,
          "25x": 0,
          "50x": 0,
          "100x": 0
        },
        {
          "price": 25.18,
          "value": 67727.696244,
          "cumulative": 245327.696244,
          "10x": 67727.696244,
          "25x": 0,
          "50x": 0,
          "100x": 0
        },
        {
          "price": 26.58,
          "value": 177600.0,
          "cumulative": 177600.0,
          "10x": 177600.0,
          "25x": 0,
          "50x": 0,
          "100x": 0
        }
      ],
      "shortLiquidations": [
        {
          "price": 31.14,
          "value": 10010.80987,
          "cumulative": 10010.80987,
          "10x": 10010.80987,
          "25x": 0,
          "50x": 0,
          "100x": 0
        },
        {
          "price": 33.94,
          "value": 355080.816587,
          "cumulative": 365091.626457,
          "10x": 355080.816587,
          "25x": 0,
          "50x": 0,
          "100x": 0
        }
      ],
      "totalLongValue": 501897.794946,
      "totalShortValue": 365091.626457,
      "positionCount": 38
    },
    "XRP": {
      "currentPrice": 1.4082,
      "longLiquidations": [],
      "shortLiquidations": [],
      "totalLongValue": 0,
      "totalShortValue": 0,
      "positionCount": 17
    },
    "DOGE": {
      "currentPrice": 0.096573,
      "longLiquidations": [],
      "shortLiquidations": [],
      "totalLongValue": 0,
      "totalShortValue": 0,
      "positionCount": 14
    },
    "SUI": {
      "currentPrice": 0.92647,
      "longLiquidations": [],
      "shortLiquidations": [],
      "totalLongValue": 0,
      "totalShortValue": 0,
      "positionCount": 10
    },
    "LINK": {
      "currentPrice": 8.7478,
      "longLiquidations": [],
      "shortLiquidations": [],
      "totalLongValue": 0,
      "totalShortValue": 0,
      "positionCount": 15
    },
    "AVAX": {
      "currentPrice": 8.9268,
      "longLiquidations": [],
      "shortLiquidations": [],
      "totalLongValue": 0,
      "totalShortValue": 0,
      "positionCount": 13
    }
  },
  "leverageBuckets": [
    {
      "min": 1,
      "max": 10,
      "label": "10x",
      "color": "#3b82f6"
    },
    {
      "min": 11,
      "max": 25,
      "label": "25x",
      "color": "#eab308"
    },
    {
      "min": 26,
      "max": 50,
      "label": "50x",
      "color": "#f97316"
    },
    {
      "min": 51,
      "max": 100,
      "label": "100x",
      "color": "#ef4444"
    }
  ],
  "tradersCount": 200,
  "lastUpdated": "2026-02-22T12:50:43.456546Z"
}